iOSbackup/__init__.py
iOSbackup-0.9.925.dist-info/METADATA
iOSbackup-0.9.925.dist-info/WHEEL
iOSbackup-0.9.925.dist-info/top_level.txt
iOSbackup-0.9.925.dist-info/RECORD
