Metadata-Version: 2.1
Name: iOSbackup
Version: 0.9.925
Summary: Reads and extracts files from password-encrypted iOS backups
Home-page: https://github.com/avibrazil/iOSbackup
Author: Avi Alkalay
Author-email: avibrazil@gmail.com
License: UNKNOWN
Platform: UNKNOWN
Classifier: Programming Language :: Python :: 3
Classifier: Operating System :: OS Independent
Classifier: Development Status :: 4 - Beta
Classifier: Environment :: MacOS X
Classifier: Environment :: Console
Classifier: Environment :: Win32 (MS Windows)
Classifier: Intended Audience :: Developers
Classifier: Intended Audience :: End Users/Desktop
Classifier: Intended Audience :: Legal Industry
Classifier: Intended Audience :: Telecommunications Industry
Classifier: License :: OSI Approved :: GNU Library or Lesser General Public License (LGPL)
Classifier: Operating System :: MacOS
Classifier: Operating System :: iOS
Classifier: Operating System :: Microsoft :: Windows
Classifier: Operating System :: POSIX
Classifier: Operating System :: Unix
Classifier: Topic :: Database
Classifier: Topic :: Security :: Cryptography
Classifier: Topic :: Software Development :: Embedded Systems
Classifier: Topic :: Software Development :: Libraries :: Python Modules
Classifier: Topic :: System :: Archiving :: Backup
Classifier: Topic :: System :: Recovery Tools
Requires-Python: >=3.7
